pyWBE/__init__.py
pyWBE/exceptions.py
pyWBE/hello.py
pyWBE/preliminary_functions.py
pyWBE/py.typed
pyWBE-0.0.6.dist-info/METADATA
pyWBE-0.0.6.dist-info/WHEEL
pyWBE-0.0.6.dist-info/top_level.txt
pyWBE-0.0.6.dist-info/RECORD
